Linux/Example/4_5RTL/iverilog/timer.v
/* ------------------------------------------------------------------------
日付　　： 2020/04/24
名前	: timer
機能	:
設計者	：アイン
確認者	：花盛
Icarus cmd: iverilog timer.v timer_tb.v -o timer_tb.o
			vvp timer_tb.o -> logfile.txt
            gtkwave timer.vcd
------------------------------------------------------------------------ */
`timescale 1ns/1ps
/* for main definiton */

 `define CNT1 3      //  number bit data of counter 1

 `define CNT2 3      //  number bit data of counter 2

 `define COMP 3      //  number bit data of comp_out

 `define ADDR 1

 `define WDATA 7

 `define RDATA 7 

 `define DEFAULT1  8'h00  // default startstop value

 `define DEFAULT2  8'h99  // default timer value

/* for testbench definiton */

 `define WIDTH1 10000    // =10us

 `define WIDTH2 50000    // SW = 4'h4 -> tout_100 = 50us and WIDTH2 = 50000

 `define WIDTH3 100000   // SW = 4'h9 -> tout_100 = 100us and WIDTH2 = 100000
 
 
 module timer(
  clk,rst_n,sel,tout_10,tout_100,
  read,write,addr,wdata,rdata
  );
/* ----- input/ output ----- */
  input clk,rst_n,sel;
  input read,write;              //read and write input signal
  input [`ADDR:0] addr;         // address input
  input [`WDATA:0]wdata;       // write data input
  output[`RDATA:0]rdata;      // read data output
  output reg tout_10;        // timer output
  output reg tout_100;      // timer output
  
  
  reg clk2,sel1,sel_out,cnt_adj;	
  reg [`CNT1:0]cnt1;     // number of bits counter 1
  reg [`CNT2:0]cnt2;     // number of bits counter 2
  wire clk_out;
  wire[`COMP:0] comp_out;
  wire flag1,flag2,comb;
  
  wire [7:0]startstop;     
  wire [7:0]timer1;          
  wire [7:0]timer2;         
  
  wire start_flag,clrcnt_flag;
  wire [3:0]CMP1_flagA,CMP1_flagB,CMP2_flagA,CMP2_flagB;         // compare flag
  parameter UD=1; // Unit delay

/* -----Multiplexer------ */   
  assign clk_out = (sel_out==1'b0) ? clk : clk2;                 // change clock 
  assign comp_out = (sel_out==1'b0) ? CMP1_flagA : CMP1_flagB;   // sel_out=0 comp_out=9 or sel_out=1 comp_out=4
  
/* -----Output of comparator-----  */ 
  assign  flag1 =(cnt1 == comp_out)?1:0;
  assign  flag2 =(cnt2 == CMP2_flagA)?1:0;
  assign  comb = flag1 && flag2;   
  
  wire clr_comb;     // if start_flag = 0 and clrcnt_flag = 1, clear counter
  assign clr_comb = clrcnt_flag & ~start_flag ;
  //assign clr_cnt2 = clr_comb | flag2;

/*  write enable data flag */
  wire WE1,WE2,WE3;
  assign WE1 = (write && (addr[`ADDR:0] == 2'b00)) ? 1 :0; 
  assign WE2 = (write && (addr[`ADDR:0] == 2'b01)) ? 1 :0;
  assign WE3 = (write && (addr[`ADDR:0] == 2'b10)) ? 1 :0;
  
/*  start/stop clear flag */
  assign start_flag  = startstop[0];
  assign clrcnt_flag = startstop[7];
/*  counter 1 compare flag  */
  assign CMP1_flagA  = timer1[3:0]; 
  assign CMP1_flagB  = timer1[7:4];
/*  counter 2 compare flag  */
  assign CMP2_flagA  = timer2[3:0];
  assign CMP2_flagB  = timer2[7:4];
  
  
  assign startstop[7:0] = (rst_n==1'b0) ? `DEFAULT1 :                     // default stage: startstop = 8'h00   
						  (WE1==1'b1) ? wdata[7:0]  : startstop[7:0];  // enable flag = 1 write data into startstop register				  
  assign timer1[7:0]    = (rst_n==1'b0) ? `DEFAULT2 :                     // default stage: timer1 = 8'h99   
                          (WE2==1'b1) ? wdata[7:0]  : timer1[7:0];     // enable flag = 1 write data into timer1 register
  assign timer2[7:0]    = (rst_n==1'b0) ? `DEFAULT2 :                     // default stage: timer2 = 8'h99   
                          (WE3==1'b1) ? wdata[7:0]  : timer2[7:0];  	  // enable flag = 1 write data into timer2 register				   
/* read data in register */
  wire RE1,RE2,RE3;
  assign RE1 = (read && (addr[`ADDR:0] == 2'b00)) ? 1 :0;
  assign RE2 = (read && (addr[`ADDR:0] == 2'b01)) ? 1 :0;
  assign RE3 = (read && (addr[`ADDR:0] == 2'b10)) ? 1 :0;
  
  assign rdata[7:0] = (RE1==1'b1)? {startstop[7],6'h00,startstop[0]}:
                      (RE2==1'b1)? {CMP1_flagB[3:0],CMP1_flagA[3:0]}:
			          (RE3==1'b1)? {CMP2_flagB[3:0],CMP2_flagA[3:0]}: 8'h0;
				 
/* -----Clock divider------ */  
  always @(posedge clk or negedge rst_n) begin
  if(rst_n==1'b0)
     clk2 <= #(UD) 1'b0;             // UDが抜けているところを直した
  else
	 clk2 <= #(UD)~clk2;            // clk2 = 0.5 Mhz
  end
/* -----synchronization------ */   
  always @(posedge clk2 or negedge rst_n) begin  // synchronized sel1 with clk2 
  if (rst_n == 1'b0)
     sel1 <= #(UD)1'b0;
  else
     sel1 <= #(UD)sel;
  end  
  always @(posedge clk2 or negedge rst_n) begin  // synchronized sel_out with clk2 and comb
  if (rst_n == 1'b0)
     sel_out <= #(UD)1'b0;
  else if(comb == 1'b0)
     sel_out <= #(UD)sel_out;  
  else
	 sel_out <= #(UD)sel1;
  end
/* ----------Timer 1 ----------- */
  always @(posedge clk) begin   // cnt_adj 同期リセット　　　同期リセットで抜けるとろこを直した。
    if (clr_comb)
	 cnt_adj = #(UD) 1'b0;
  end
  always @(posedge clk2 or negedge rst_n) begin  // adjusting counter1 signal
  if(rst_n == 1'b0)             
     cnt_adj <= #(UD)1'b0;
  else if ((clr_comb == 1'b0) && (rst_n == 1'b1))
     cnt_adj <= #(UD)1'b1;
  end  
  
  always @(posedge clk) begin   // cnt1 同期リセット
     if (clr_comb)
	 cnt1 = #(UD) 1'b0;
  end   
  always @(posedge clk_out or negedge rst_n)begin  //Counter1 4bits
  if(rst_n == 1'b0)                      //  reset　非同期
     cnt1 <= #(UD)1'b0; 
  else if (cnt_adj == 1'b0 || flag1 == 1'b1) 
     cnt1 <= #(UD) 1'b0 ;  //  reset　非同期
  else if(start_flag && cnt_adj)
     cnt1 <= #(UD) cnt1+1;  
  end
  
  always @(posedge clk_out or negedge rst_n) begin  //DFF4
  if(rst_n == 1'b0)                     //  reset　非同期
     tout_10 <= #(UD)1'b0;
  else 
     tout_10 <= #(UD)(flag1==1) ? 1 : 0;         //  reset　非同期
  end
  
  /* ----------Timer 2 ----------- */
  always @(posedge clk) begin   // cnt2 同期リセット　　　　同期リセットで抜けるとろこを直した。
     if (clr_comb)
	 cnt2 = #(UD) 1'b0;
  end 
  always @(posedge clk_out or negedge rst_n) begin   //Counter2 4bits
  if(rst_n==1'b0)                          //  reset　非同期
     cnt2 <= #(UD)1'b0;
  else if ( comb ) 
     cnt2<=#(UD)1'b0; 
  else if(flag1)                          
     cnt2<=#(UD) cnt2+1;      //  reset　非同期
  end  

  always @(posedge clk_out or negedge rst_n) begin  //DFF5
  if(rst_n == 1'b0)                      //  reset　非同期
     tout_100 <= #(UD)1'b0;
  else 
     tout_100 <= #(UD)(comb == 1) ? 1 : 0;   // AND gate flag1, flag2
  end
  endmodule

Linux/Example/4_5RTL/timer_tb.v
/* ------------------------------------------------------------------------
日付　　： 2020/04/24
名前	: timer_tb
機能	: 
設計者	：アイン
確認者	：花盛
Icarus cmd: iverilog timer.v timer_tb.v -o timer_tb.o
			vvp timer_tb.o -> logfile.txt
            gtkwave timer.vcd
------------------------------------------------------------------------ */
`timescale 1ns/1ps

/* for main definiton */

 `define CNT1 3      //  number bit data of counter 1

 `define CNT2 3      //  number bit data of counter 2

 `define COMP 3      //  number bit data of comp_out

 `define ADDR 1

 `define WDATA 7

 `define RDATA 7 

 `define DEFAULT1  8'h00  // default startstop value

 `define DEFAULT2  8'h99  // default timer value

/* for testbench definiton */

 `define WIDTH1 10000    // =10us

 `define WIDTH2 50000    // SW = 4'h4 -> tout_100 = 50us and WIDTH2 = 50000

 `define WIDTH3 100000   // SW = 4'h9 -> tout_100 = 100us and WIDTH2 = 100000
 
 
module timer_tb;
reg clk,rst_n,sel;
reg read,write;
reg [1:0]addr;
reg [7:0]wdata;

wire [7:0]rdata;
wire tout_10;
wire tout_100;

parameter CYC =1000; // clock period 1us
integer i,j;
/* ------DUT Instantiation------ */
timer tb(
.clk (clk),
.rst_n (rst_n),
.sel (sel),
.write (write),
.read (read),
.addr (addr),
.wdata (wdata),
.rdata (rdata),
.tout_10 (tout_10),
.tout_100 (tout_100)
);
/* -------初期値セット--------- */
 initial begin
     clk = 1'b0;rst_n = 1'b0; sel = 1'b0;
	 write = 1'b0;read = 1'b0;wdata=8'h00;
 end
/* -------1MHZクロックを作成-------- */
initial begin
forever #(CYC/2) clk = !clk;
end

// coverage off
/* Display reset event in the logfile */
 always @( rst_n) begin   // Notifications  have a reset event
  if (rst_n)
     $display(" Reset = 1   Time: %t ", $realtime);
  else
     $display(" Reset = 0   Time: %t", $realtime);
     $timeformat(-6, 3, " us", 12);  
  end

 always @(sel)  
   begin
     if (sel ==1'b0) 
	 $display(" Select = 0    1Mhz     Time: %t", $realtime);
	 else if (sel ==1'b1) 
	 $display(" Select = 1    0.5Mhz    Time: %t", $realtime);
	 $timeformat(-6, 3, " us", 12);  
  end
  
/* --------timer の幅を表示する-------- */
 real edge10,edge100;
/* -timer 10us の幅を表示する- */
 always@(rst_n) begin
  if(rst_n==0) 
     i=0;j=0;
  end
 always @(posedge tout_10) begin
     i = i+1;
	 edge10 <= $realtime;
     $timeformat(-6, 3, " us", 12);  
 if (i>=2)   // intervalの計算のは tout_10の１周期がディレイ
   if ( (($realtime-edge10) >= `WIDTH1-1) && (($realtime-edge10) <= `WIDTH1+1) )
     $display("interval_num_%2d",i-1,"    In fact tout_10 = %t", ($realtime-edge10)," - PASS  "," at time: ",$realtime); 
   else 
     $display("interval_num_%2d",i-1,"    In fact tout_10 = %t", ($realtime-edge10)," - FAIL  "," at time: ",$realtime); 
end

always @(posedge tout_100) begin
     j = j+1;
     edge100 <= $realtime;
   $timeformat(-6, 3, " us", 12);  
 if (j>=2)   // intervalの計算のは tout_10の１周期がディレイ
   if ( (($realtime-edge100) >= `WIDTH2-1) && (($realtime-edge100) <= `WIDTH2+1) )
   $display("\ninterval_num_%2d",j-1,"    In fact tout_100 = %t", ($realtime-edge100)," - PASS  ","at time: ",$realtime,"  setup tout_100 = 50us \n"); 
   else if ( (($realtime-edge100) >= `WIDTH3-1) && (($realtime-edge100) >= `WIDTH3+1)  )
   $display("\ninterval_num_%2d",j-1,"    In fact tout_100 = %t", ($realtime-edge100)," - PASS  ","at time: ",$realtime,"  setup tout_100 = 100us \n"); 
   else 
   $display("\ninterval_num_%2d",j-1,"    In fact tout_100 = %t", ($realtime-edge100)," - FAIL  ","at time: ",$realtime,"\n"); 
end 

/* write data in Block function */
task WRITE_DATA;
input [1:0]W_ADDR;
input [7:0]W_DATA ;
  begin
     // #(CYC*1) 
	 addr = W_ADDR;
	 wdata = W_DATA;#(CYC*1) 
     write =1'b1;#(CYC*1) 
	 write=1'b0;addr[1:0]= 2'b00;#1
	 wdata=1'b0;
  end
 endtask
 // coverage off
/* read data in Block function */
 task READ_DATA;
 input [1:0]R_ADDR;
  begin
     addr[1:0] = R_ADDR[1:0];#(CYC*1)
	 read = 1'b1; #1 
	case (addr)
	2'b00: $display("At address %2b  :   Data in the startstop register = %h",addr,rdata,"　  at time: ",$realtime); 
	2'b01: $display("At address %2b  :   Data in the timer1 register    = %h",addr,rdata,"　  at time: ",$realtime);
	2'b10: $display("At address %2b  :   Data in the timer2 register    = %h",addr,rdata,"　  at time: ",$realtime);
	endcase
	#(CYC*1)
	 read=1'b0;addr[1:0]= 2'b00;
  end
 endtask
 // coverage on 
 
 /*   -----------------------TEST PATTERN------------------------ */
initial begin
// insert on

$finish;     // Simulation STOP条件
end
endmodule

Linux/Example/4_5RTL/covered/TP_001_tb.vcd
$date
	Mon Oct  5 10:40:03 2020
$end
$version
	Icarus Verilog
$end
$timescale
	1ps
$end
$scope module timer_tb $end
$var wire 1 ! tout_100 $end
$var wire 1 " tout_10 $end
$var wire 8 # rdata [7:0] $end
$var reg 2 $ addr [1:0] $end
$var reg 1 % clk $end
$var reg 1 & read $end
$var reg 1 ' rst_n $end
$var reg 1 ( sel $end
$var reg 8 ) wdata [7:0] $end
$var reg 1 * write $end
$var real 1 + edge10 $end
$var real 1 , edge100 $end
$var integer 32 - i [31:0] $end
$var integer 32 . j [31:0] $end
$scope module tb $end
$var wire 2 / addr [1:0] $end
$var wire 1 % clk $end
$var wire 1 0 clr_comb $end
$var wire 1 1 comb $end
$var wire 1 & read $end
$var wire 1 ' rst_n $end
$var wire 1 ( sel $end
$var wire 8 2 wdata [7:0] $end
$var wire 1 * write $end
$var wire 8 3 timer2 [7:0] $end
$var wire 8 4 timer1 [7:0] $end
$var wire 8 5 startstop [7:0] $end
$var wire 1 6 start_flag $end
$var wire 8 7 rdata [7:0] $end
$var wire 1 8 flag2 $end
$var wire 1 9 flag1 $end
$var wire 4 : comp_out [3:0] $end
$var wire 1 ; clrcnt_flag $end
$var wire 1 < clk_out $end
$var wire 1 = WE3 $end
$var wire 1 > WE2 $end
$var wire 1 ? WE1 $end
$var wire 1 @ RE3 $end
$var wire 1 A RE2 $end
$var wire 1 B RE1 $end
$var wire 4 C CMP2_flagB [3:0] $end
$var wire 4 D CMP2_flagA [3:0] $end
$var wire 4 E CMP1_flagB [3:0] $end
$var wire 4 F CMP1_flagA [3:0] $end
$var reg 1 G clk2 $end
$var reg 4 H cnt1 [3:0] $end
$var reg 4 I cnt2 [3:0] $end
$var reg 1 J cnt_adj $end
$var reg 1 K sel1 $end
$var reg 1 L sel_out $end
$var reg 1 " tout_10 $end
$var reg 1 ! tout_100 $end
$upscope $end
$scope task READ_DATA $end
$var reg 2 M R_ADDR [1:0] $end
$upscope $end
$scope task WRITE_DATA $end
$var reg 2 N W_ADDR [1:0] $end
$var reg 8 O W_DATA [7:0] $end
$upscope $end
$upscope $end
$enddefinitions $end
#0
$dumpvars
bx O
bx N
b0 M
xL
xK
xJ
bx I
bx H
xG
b1001 F
b1001 E
b1001 D
b1001 C
0B
0A
0@
0?
0>
0=
x<
0;
b1001 :
x9
x8
b0 7
06
b0 5
b10011001 4
b10011001 3
b0 2
x1
00
b0 /
b0 .
b0 -
r0 ,
r0 +
0*
b0 )
0(
0'
0&
0%
b0 $
b0 #
x"
x!
$end
#1000
01
09
08
0<
b0 H
0"
b0 I
0!
0K
0L
0J
0G
#500000
1<
1%
#1000000
1B
0<
0%
1&
#1500000
1<
1%
#2000000
0<
0%
#2001000
0B
b1 $
b1 /
b1 M
0&
#2500000
1<
1%
#3000000
0<
0%
#3001000
b10011001 #
b10011001 7
1A
1&
#3500000
1<
1%
#4000000
0<
0%
#4002000
b0 #
b0 7
0A
b10 M
b10 $
b10 /
0&
#4500000
1<
1%
#5000000
0<
0%
#5002000
b10011001 #
b10011001 7
1@
1&
#5500000
1<
1%
#6000000
0<
0%
#6003000
b0 #
b0 7
0@
b10000000 )
b10000000 2
b10000000 O
b0 N
b0 $
b0 /
0&
#6500000
1<
1%
#7000000
0<
0%
#7003000
1?
1*
#7500000
1<
1%
#8000000
0<
0%
#8003000
0?
0*
#8004000
b1 O
b1 )
b1 2
#8500000
1<
1%
#9000000
0<
0%
#9004000
1?
1*
#9500000
1<
1%
#10000000
0<
0%
#10004000
0?
0*
#10005000
b1 $
b1 /
b1001001 O
b1 N
b1001001 )
b1001001 2
#10500000
1<
1%
#11000000
0<
0%
#11005000
1>
1*
#11500000
1<
1%
#12000000
0<
0%
#12005000
0>
b0 $
b0 /
0*
#12006000
b10 $
b10 /
b1001 O
b10 N
b1001 )
b1001 2
#12500000
1<
1%
#13000000
0<
0%
#13006000
1=
1*
#13500000
1<
1%
#14000000
0<
0%
#14006000
0=
b0 $
b0 /
0*
#14007000
b0 )
b0 2
